oneNeuron/__init__.py
oneNeuron/perceptron.py
oneNeuron_pkg_c17hawke-0.0.3.dist-info/LICENSE
oneNeuron_pkg_c17hawke-0.0.3.dist-info/METADATA
oneNeuron_pkg_c17hawke-0.0.3.dist-info/WHEEL
oneNeuron_pkg_c17hawke-0.0.3.dist-info/top_level.txt
oneNeuron_pkg_c17hawke-0.0.3.dist-info/RECORD
