Metadata-Version: 2.1
Name: oneNeuron-pkg-c17hawke
Version: 0.0.3
Summary: A small package for perceptron
Home-page: https://github.com/c17hawke/oneNeuron-pkg
Author: c17hawke
Author-email: sunny.c17hawke@gmail.com
License: UNKNOWN
Project-URL: Bug Tracker, https://github.com/c17hawke/oneNeuron-pkg/issues
Platform: UNKNOWN
Classifier: Programming Language :: Python :: 3
Classifier: License :: OSI Approved :: MIT License
Classifier: Operating System :: OS Independent
Requires-Python: >=3.6
License-File: LICENSE
Requires-Dist: numpy (==1.21.4)
Requires-Dist: pandas (==1.3.4)
Requires-Dist: joblib (==1.1.0)
